Metadata-Version: 2.1
Name: UltimateChemCalc
Version: 3.0
Summary: A collection of chemistry-related conversion calculators.
Home-page: https://www.inventorsniche.com
Author: Harold J. Iwen
Author-email: inventorsniche349@gmail.com
License: MIT
Download-URL: https://github.com/Hiwen-STEM/UltimateChemCalc
Keywords: Chemistry,Mole,Stoichiometry,Conversion,Chemical,Equation
Platform: UNKNOWN
Classifier: Development Status :: 3 - Alpha
Classifier: Intended Audience :: Developers
Classifier: Topic :: Software Development :: Build Tools
Classifier: License :: OSI Approved :: MIT License
Classifier: Programming Language :: Python :: 3.6
Classifier: Programming Language :: Python :: 3.7
Classifier: Programming Language :: Python :: 3.8
